chorusmatcher/__init__.py
chorusmatcher/api.py
chorusmatcher/folders.py
chorusmatcher/logic.py
chorusmatcher/main.py
chorusmatcher-0.1.2.dist-info/LICENSE
chorusmatcher-0.1.2.dist-info/METADATA
chorusmatcher-0.1.2.dist-info/WHEEL
chorusmatcher-0.1.2.dist-info/entry_points.txt
chorusmatcher-0.1.2.dist-info/top_level.txt
chorusmatcher-0.1.2.dist-info/RECORD
