Metadata-Version: 2.1
Name: chorusmatcher
Version: 0.1.2
Requires-Python: >=3.6
License-File: LICENSE
Requires-Dist: requests
